morphy_ti/__init__.py
morphy_ti/api_client.py
morphy_ti/api_response.py
morphy_ti/configuration.py
morphy_ti/exceptions.py
morphy_ti/py.typed
morphy_ti/rest.py
morphy_ti/api/__init__.py
morphy_ti/api/default_api.py
morphy_ti/models/__init__.py
morphy_ti/models/compress_text200_response.py
morphy_ti/models/compress_text_request.py
morphy_ti/models/expand_text200_response.py
morphy_ti/models/expand_text_request.py
morphy_ti-0.0.1.dist-info/METADATA
morphy_ti-0.0.1.dist-info/WHEEL
morphy_ti-0.0.1.dist-info/top_level.txt
morphy_ti-0.0.1.dist-info/RECORD
